polars_expr_hopper-1.1.1.dist-info/METADATA
polars_expr_hopper-1.1.1.dist-info/WHEEL
polars_expr_hopper-1.1.1.dist-info/entry_points.txt
polars_expr_hopper-1.1.1.dist-info/licenses/LICENSE
polars_hopper/__init__.py
polars_expr_hopper-1.1.1.dist-info/RECORD
