Metadata-Version: 2.1
Name: polars-expr-hopper
Version: 1.1.1
Summary: A Polars plugin providing a 'hopper' of expressions for automatic, schema-aware application.
Keywords: polars,plugin,filter,expr,metadata
Author-Email: Louis Maddox <louismmx@gmail.com>
License: MIT
Classifier: Development Status :: 4 - Beta
Classifier: Intended Audience :: Developers
Classifier: License :: OSI Approved :: MIT License
Classifier: Natural Language :: English
Classifier: Operating System :: OS Independent
Classifier: Programming Language :: Python
Classifier: Programming Language :: Python :: Implementation :: CPython
Classifier: Programming Language :: Python :: 3
Classifier: Programming Language :: Python :: 3.9
Classifier: Programming Language :: Python :: 3.10
Classifier: Programming Language :: Python :: 3.11
Classifier: Programming Language :: Python :: 3.12
Classifier: Programming Language :: Python :: 3.13
Project-URL: Documentation, https://polars-expr-hopper.vercel.app/
Project-URL: Homepage, https://github.com/lmmx/polars-expr-hopper
Project-URL: Repository, https://github.com/lmmx/polars-expr-hopper.git
Requires-Python: >=3.9
Requires-Dist: polars-config-meta>=0.1.3
Provides-Extra: polars
Requires-Dist: polars>=1.21.0; extra == "polars"
Provides-Extra: polars-lts-cpu
Requires-Dist: polars-lts-cpu>=1.21.0; extra == "polars-lts-cpu"
Provides-Extra: pyarrow
Requires-Dist: polars-config-meta[pyarrow]>=0.1.3; extra == "pyarrow"
